janus/__init__.py
janus/__main__.py
janus/_tests/__init__.py
janus/_tests/conftest.py
janus/_tests/evaluator_tests/EvalReadMe.md
janus/_tests/evaluator_tests/incose_tests/incose_large_test.json
janus/_tests/evaluator_tests/incose_tests/incose_small_test.json
janus/_tests/evaluator_tests/inline_comment_tests/mumps_inline_comment_test.m
janus/_tests/test_cli.py
janus/cli/aggregate.py
janus/cli/cli.py
janus/cli/constants.py
janus/cli/database.py
janus/cli/diagram.py
janus/cli/document.py
janus/cli/embedding.py
janus/cli/llm.py
janus/cli/partition.py
janus/cli/pipeline.py
janus/cli/self_eval.py
janus/cli/translate.py
janus/converter/__init__.py
janus/converter/_tests/__init__.py
janus/converter/_tests/test_translate.py
janus/converter/aggregator.py
janus/converter/chain.py
janus/converter/converter.py
janus/converter/diagram.py
janus/converter/document.py
janus/converter/evaluate.py
janus/converter/partition.py
janus/converter/passthrough.py
janus/converter/pool.py
janus/converter/requirements.py
janus/converter/translate.py
janus/embedding/__init__.py
janus/embedding/_tests/__init__.py
janus/embedding/_tests/test_collections.py
janus/embedding/_tests/test_database.py
janus/embedding/_tests/test_vectorize.py
janus/embedding/collections.py
janus/embedding/database.py
janus/embedding/embedding_models_info.py
janus/embedding/vectorize.py
janus/language/__init__.py
janus/language/_tests/__init__.py
janus/language/_tests/test_combine.py
janus/language/_tests/test_splitter.py
janus/language/alc/__init__.py
janus/language/alc/_tests/__init__.py
janus/language/alc/_tests/alc.asm
janus/language/alc/_tests/test_alc.py
janus/language/alc/alc.py
janus/language/binary/__init__.py
janus/language/binary/_tests/__init__.py
janus/language/binary/_tests/hello.bin
janus/language/binary/_tests/test_binary.py
janus/language/binary/binary.py
janus/language/binary/reveng/decompile_script.py
janus/language/block.py
janus/language/combine.py
janus/language/file.py
janus_llm-4.5.4.dist-info/LICENSE
janus_llm-4.5.4.dist-info/METADATA
janus_llm-4.5.4.dist-info/WHEEL
janus_llm-4.5.4.dist-info/entry_points.txt
janus_llm-4.5.4.dist-info/RECORD
