Metadata-Version: 2.3
Name: janus-llm
Version: 4.5.4
Summary: A transcoding library using LLMs.
License: Apache 2.0
Author: Michael Doyle
Author-email: mdoyle@mitre.org
Requires-Python: >=3.11,<3.13
Classifier: License :: Other/Proprietary License
Classifier: Programming Language :: Python :: 3
Classifier: Programming Language :: Python :: 3.11
Classifier: Programming Language :: Python :: 3.12
Provides-Extra: all
Provides-Extra: bedrock
Provides-Extra: hf-local
Requires-Dist: aenum (>=3.1.15,<4.0.0)
Requires-Dist: boto3 (>=1.34.142,<2.0.0) ; extra == "bedrock" or extra == "all"
Requires-Dist: chromadb (>=0.5.21,<0.6.0)
Requires-Dist: gitpython (>=3.1.32,<4.0.0)
Requires-Dist: gpt4all (>=2.0.2,<3.0.0)
Requires-Dist: langchain (>=0.2.0,<0.3.0)
Requires-Dist: langchain-anthropic (>=0.1.15,<0.2.0)
Requires-Dist: langchain-community (>=0.2.0,<0.3.0)
Requires-Dist: langchain-core (>=0.2.0,<0.3.0)
Requires-Dist: langchain-openai (>=0.1.8,<0.2.0)
Requires-Dist: langchain-unstructured (>=0.1.2,<0.2.0)
Requires-Dist: numpy (>=1.24.3,<2.0.0)
Requires-Dist: openai (>=1.14.0,<2.0.0)
Requires-Dist: pi-heif (>=0.20.0,<0.21.0)
Requires-Dist: pybind11 (>=2.13.6,<3.0.0)
Requires-Dist: pytesseract (>=0.3.13,<0.4.0)
Requires-Dist: python-dotenv (>=1.0.0,<2.0.0)
Requires-Dist: rich (>=13.7.1,<14.0.0)
Requires-Dist: rouge-score (>=0.1.2,<0.2.0)
Requires-Dist: sacrebleu (>=2.4.1,<3.0.0)
Requires-Dist: scikit-learn (>=1.5.2,<2.0.0)
Requires-Dist: sentence-transformers (>=2.6.1,<3.0.0) ; extra == "hf-local" or extra == "all"
Requires-Dist: setuptools (>=75.6.0,<76.0.0)
Requires-Dist: tesseract (>=0.1.3,<0.2.0)
Requires-Dist: text-generation (>=0.6.0,<0.7.0)
Requires-Dist: textstat (>=0.7.5,<0.8.0)
Requires-Dist: tiktoken (>=0.7.0,<0.8.0)
Requires-Dist: transformers (>=4.31.0,<5.0.0)
Requires-Dist: tree-sitter (>=0.21.0,<0.22.0)
Requires-Dist: typer (>=0.9.0,<0.10.0)
Requires-Dist: unstructured (>=0.15.9,<0.16.0)
Requires-Dist: unstructured-inference (>=0.7.36,<0.8.0)
Requires-Dist: unstructured-pytesseract (>=0.3.13,<0.4.0)
Project-URL: Documentation, https://janus-llm.github.io/janus-llm
Project-URL: Repository, https://github.com/janus-llm/janus-llm
